type_annotations_generator.py
type_annotations_generator-1.0.dist-info/LICENSE
type_annotations_generator-1.0.dist-info/METADATA
type_annotations_generator-1.0.dist-info/WHEEL
type_annotations_generator-1.0.dist-info/top_level.txt
type_annotations_generator-1.0.dist-info/RECORD
